dof/__init__.py
dof/core.py
dof/data.py
dof/datamodel.py
dof/error.py
dof/file.py
dof/information.py
dof/services.py
dof/storage.py
dofpy-2.0.1.dist-info/LICENSE
dofpy-2.0.1.dist-info/METADATA
dofpy-2.0.1.dist-info/WHEEL
dofpy-2.0.1.dist-info/top_level.txt
dofpy-2.0.1.dist-info/RECORD
