Metadata-Version: 2.1
Name: dofpy
Version: 2.0.1
Summary: Deep Model Core Output Framework
Home-page: https://github.com/hyperrixel/dof
Author: Axel Ország-Krisz Dr., Richárd Ádám Vécsey Dr.
Author-email: dof@hyperrixel.com
License: UNKNOWN
Project-URL: Bug Tracker, https://github.com/hyperrixel/dof/issues
Platform: UNKNOWN
Classifier: Programming Language :: Python :: 3
Classifier: License :: OSI Approved :: MIT License
Classifier: Operating System :: OS Independent
Requires-Python: >=3.7
